setup.cfg
setup.py
chatopera/__init__.py
chatopera/chatbot.py
chatopera/chatopera.py
chatopera/misc.py
chatopera.egg-info/PKG-INFO
chatopera.egg-info/SOURCES.txt
chatopera.egg-info/dependency_links.txt
chatopera.egg-info/requires.txt
chatopera.egg-info/top_level.txt