Metadata-Version: 1.1
Name: chatopera
Version: 2.2.2
Summary: 定制化聊天机器人服务
Home-page: https://github.com/chatopera/chatopera-py-sdk
Author: Hai Liang Wang
Author-email: hain@chatopera.com
License: Apache Software License
Keywords: chatbot,machine-learning,IR
Platform: UNKNOWN
Classifier: Intended Audience :: Developers
Classifier: License :: OSI Approved :: Apache Software License
Classifier: Operating System :: OS Independent
Classifier: Natural Language :: English
Classifier: Natural Language :: Chinese (Simplified)
Classifier: Programming Language :: Python
Classifier: Programming Language :: Python :: 3
Classifier: Programming Language :: Python :: 2
Classifier: Topic :: Communications :: Chat
Classifier: Topic :: Text Processing :: Indexing
Classifier: Topic :: Text Processing :: Linguistic
